mdv/__init__.py
mdv/ansi_tables.json
mdv/markdownviewer.py
mdv/tabulate.py
mdv/misc/.test_md.md.swp
mdv/misc/perfest.py
mdv/misc/test_md.md
mdv/misc/results_perftests/out_commonmark.html
mdv/misc/results_perftests/out_markdown.html
mdv/misc/results_perftests/out_mistletoe.html
mdv/misc/results_perftests/out_mistletoe_ansi.html
mdv/misc/results_perftests/out_paka.html
mdv/misc/results_perftests/out_paka_breaks.html
mdv/misc/results_perftests/out_paka_xml.html
mdv/tests/__init__.py
mdv/tests/test_files.py
mdv/tests/test_inline.py
mdv/tests/files/README.md
mdv/tests/files/blockquotes.md
mdv/tests/files/issue_52.md
mdv/tests/files/links.md
mdv/tests/files/nested_lists.md
mdv/tests/files/readme_example.md
mdv/tests/files/run
mdv/tests/files/test1.md
mdv/tests/files/test_fenced.md
mdv/tests/files/manual/issue_10.md
mdv/tests/files/manual/js.js
mdv/tests/files/manual/lists.md
mdv/tests/files/manual/lists_simple.md
mdv/tests/files/manual/lists_with_inline.md
mdv/tests/files/manual/main_example.md
mdv/tests/files/manual/ol.md
mdv/tests/files/manual/run_all.py
mdv/tests/files/manual/wrap1.md
mdv/tests/files/result.20/README.md.expected
mdv/tests/files/result.20/blockquotes.md.expected
mdv/tests/files/result.20/issue_52.md.expected
mdv/tests/files/result.20/links.md.expected
mdv/tests/files/result.20/nested_lists.md.expected
mdv/tests/files/result.20/readme_example.md.expected
mdv/tests/files/result.20/test1.md.expected
mdv/tests/files/result.20/test_fenced.md.expected
mdv/tests/files/result.200/README.md.expected
mdv/tests/files/result.200/blockquotes.md.expected
mdv/tests/files/result.200/issue_52.md.expected
mdv/tests/files/result.200/links.md.expected
mdv/tests/files/result.200/nested_lists.md.expected
mdv/tests/files/result.200/readme_example.md.expected
mdv/tests/files/result.200/test1.md.expected
mdv/tests/files/result.200/test_fenced.md.expected
mdv/tests/files/result.40/README.md.expected
mdv/tests/files/result.40/blockquotes.md.expected
frkl.mdv-1.7.5.dist-info/LICENSE
frkl.mdv-1.7.5.dist-info/LICENSE.txt
frkl.mdv-1.7.5.dist-info/METADATA
frkl.mdv-1.7.5.dist-info/WHEEL
frkl.mdv-1.7.5.dist-info/entry_points.txt
frkl.mdv-1.7.5.dist-info/top_level.txt
frkl.mdv-1.7.5.dist-info/RECORD
