Metadata-Version: 2.1
Name: frkl.mdv
Version: 1.7.5
Summary: Terminal Markdown Viewer
Home-page: http://github.com/axiros/terminal_markdown_viewer
Author: Axiros GmbH
Author-email: gk@axiros.com
License: UNKNOWN
Download-URL: http://github.com/axiros/terminal_markdown_viewer/tarball/
Keywords: markdown,markup,terminal,hilighting,syntax,source code
Platform: UNKNOWN
Classifier: Programming Language :: Python
Classifier: Natural Language :: English
Classifier: Operating System :: POSIX
Classifier: Topic :: Text Processing :: Markup
Classifier: License :: OSI Approved :: BSD License
Classifier: Programming Language :: Python :: 2.7
Classifier: Programming Language :: Python :: 3.6
Classifier: Programming Language :: Python :: 3.7
Requires-Dist: tabulate
Requires-Dist: pygments
Requires-Dist: markdown
Provides-Extra: yaml
Requires-Dist: pyyaml ; extra == 'yaml'
